tree_sitter_languages_freed_wu_pr/core.cpython-312-aarch64-linux-musl.so
tree_sitter_languages_freed_wu_pr/languages.so
tree_sitter_languages_freed_wu_pr/__init__.py
tree_sitter_languages_freed_wu_pr-1.11.1.dist-info/top_level.txt
tree_sitter_languages_freed_wu_pr-1.11.1.dist-info/RECORD
tree_sitter_languages_freed_wu_pr-1.11.1.dist-info/LICENSE
tree_sitter_languages_freed_wu_pr-1.11.1.dist-info/METADATA
tree_sitter_languages_freed_wu_pr-1.11.1.dist-info/WHEEL
