Metadata-Version: 2.1
Name: tree_sitter_languages_freed_wu_pr
Version: 1.11.1
Summary: Binary Python wheels for all tree sitter languages (Freed-Wu PR).
Home-page: https://github.com/grantjenks/py-tree-sitter-languages/pull/53
Author: Grant Jenks
Author-email: contact@grantjenks.com
License: Apache 2.0
Project-URL: Documentation, https://github.com/grantjenks/py-tree-sitter-languages
Project-URL: Source, https://github.com/grantjenks/py-tree-sitter-languages
Project-URL: Tracker, https://github.com/grantjenks/py-tree-sitter-languages/issues
Classifier: Development Status :: 5 - Production/Stable
Classifier: Intended Audience :: Developers
Classifier: License :: OSI Approved :: Apache Software License
Classifier: Natural Language :: English
Classifier: Programming Language :: Python
Classifier: Programming Language :: Python :: 3
Classifier: Programming Language :: Python :: Implementation :: CPython
License-File: LICENSE
Requires-Dist: tree-sitter<0.22.0
